Metadata-Version: 2.1
Name: evidencer
Version: 0.2
Summary: Framework for modular extraction information.
Home-page: https://github.com/Honzin/evidencer
Author: Jan Seda
Author-email: xsedaj00@gmail.com
License: UNKNOWN
Keywords: testing,logs,extraction
Platform: UNKNOWN
Classifier: Development Status :: 3 - Alpha
Classifier: Intended Audience :: Developers
Classifier: Programming Language :: Python :: 3.5
Classifier: Programming Language :: Python :: 3.6
Classifier: Programming Language :: Python :: 3.7
